HalfAdder/HA.v
module Half_Adder(
    input A, B,
	output Sum, Cout
	);
	assign #9 Sum = A ^ B ;
	assign #12 Cout = A & B;
endmodule

HalfAdder/HATB.v
`timescale  1ns/1ns
`include "HA.v"

module HATB;
    reg A = 0;
    reg B = 0;

    wire Sum;
    wire Carry_out;

    Half_Adder HA1 (A, B, Sum, Carry_out);

    parameter time_limit = 100;

    initial begin
        $dumpfile("Half_Adder.vcd");
        $dumpvars(0, HATB);
        #10
        A = 1; B = 0;
        #30
        A = 1; B = 1;
        #100
        A = 0; B = 0;
        #100
        $dumpoff;
        $finish;
    end
endmodule

HalfAdder/Half_Adder.vcd
$date
	Sat Sep 02 17:24:31 2023
$end
$version
	Icarus Verilog
$end
$timescale
	1ns
$end
$scope module HATB $end
$var wire 1 ! Sum $end
$var wire 1 " Carry_out $end
$var parameter 32 # time_limit $end
$var reg 1 $ A $end
$var reg 1 % B $end
$scope module HA1 $end
$var wire 1 $ A $end
$var wire 1 % B $end
$var wire 1 " Cout $end
$var wire 1 ! Sum $end
$upscope $end
$upscope $end
$enddefinitions $end
$comment Show the parameter values. $end
$dumpall
b1100100 #
$end
#0
$dumpvars
0%
0$
x"
x!
$end
#9
0!
#10
1$
#12
0"
#19
1!
#40
1%
#49
0!
#52
1"
#140
0%
0$
#152
0"
#240
$dumpoff
x%
x$
x"
x!
$end
